wwara_chirp/__init__.py
wwara_chirp/chirpvalidator.py
wwara_chirp/wwara_chirp.py
wwara_chirp-2.0.2.dist-info/licenses/LICENSE.txt
wwara_chirp-2.0.2.dist-info/METADATA
wwara_chirp-2.0.2.dist-info/WHEEL
wwara_chirp-2.0.2.dist-info/entry_points.txt
wwara_chirp-2.0.2.dist-info/top_level.txt
wwara_chirp-2.0.2.dist-info/RECORD
