Metadata-Version: 2.4
Name: wwara-chirp
Version: 2.0.2
Summary: WWARA CHIRP Export Script Update
Home-page: https://github.com/tsayles/wwara-chirp.git
Author: Tom Sayles (KE4HET)
Author-email: "Tom Sayles (KE4HET)" <tsayles@Soot-n-Smoke.com>
License: MIT
Project-URL: Bug Reports, https://github.com/tsayles/wwara-chirp/issues
Keywords: WWARA,CHIRP
Classifier: Development Status :: 4 - Beta
Classifier: Intended Audience :: Developers
Classifier: Intended Audience :: Science/Research
Classifier: Intended Audience :: Other Audience
Classifier: Topic :: Communications :: Ham Radio
Classifier: Topic :: Education
Classifier: Topic :: Scientific/Engineering
Classifier: License :: OSI Approved :: MIT License
Classifier: Programming Language :: Python :: 3.10
Classifier: Programming Language :: Python :: 3.11
Classifier: Programming Language :: Python :: 3.12
Requires-Python: >=3.6
License-File: LICENSE.txt
Dynamic: author
Dynamic: home-page
Dynamic: license-file
Dynamic: requires-python
